textbase.py
TextBase-0.9.dist-info/METADATA
TextBase-0.9.dist-info/RECORD
TextBase-0.9.dist-info/WHEEL
TextBase-0.9.dist-info/top_level.txt
