Metadata-Version: 2.1
Name: TextBase
Version: 0.9
Summary: TextBase library to manipulate DBText style data files.
Home-page: https://github.com/epoz/textbase/
Author: Etienne Posthumus
Author-email: ep@epoz.org
License: UNKNOWN
Platform: UNKNOWN
Classifier: Programming Language :: Python :: 2.7
Classifier: Programming Language :: Python :: 3
Classifier: License :: OSI Approved :: MIT License
Classifier: Operating System :: OS Independent
